<bncDoc id=BDCF5 n=AaApps>
<header creator=dominic status=UPDATE update="2 Feb 1999" type=TEXT>
<fileDesc>
<titStmt>
<title>
East Anglian daily times -- an electronic version
</title>
<respStmt>
<resp>
Data capture and transcription
</resp>
<name>
Oxford University Press
</name>
</respStmt>
</titStmt>
<ednStmt n=s1>
Header automatically generated by mkhdr 0.30
Updated for sampler by interleave 1.1
</ednStmt>
<extent words=3397 kb=72>
</extent>
<pubStmt>
<respStmt>
<resp>
Archive site
</resp>
<name>
Oxford University Computing Services
</name>
</respStmt>
<address>
13 Banbury Road, Oxford OX2 6NN U.K.
Telephone:     +44 1865 273280
Facsimile:     +44 1865 273275
Internet mail: natcorp@oucs.ox.ac.uk
</address>
<idno n=AaApps type=bnc>
AaApps
</idno>
<avail region=world status=RESTRICT>
Available worldwide

THIS TEXT IS AVAILABLE THROUGHOUT THE WORLD only as part of
the British National Corpus at nominal charge FOR ACADEMIC
RESEARCH PURPOSES SUBJECT TO A SIGNED END USER LICENCE
HAVING BEEN RECEIVED BY OXFORD UNIVERSITY COMPUTING
SERVICES, from whom forms and supporting materials are
available.

THIS TEXT IS NOT AVAILABLE FOR COMMERCIAL RESEARCH AND
EXPLOITATION unless terms have first been agreed with the
BNC Consortium Exploitation Committee.  Apply in the first
instance to Oxford University Computing Services.

It is your responsibility, as a user, to ensure that an End
User Licence is in place.  For your information, the Terms
of the End User Licence are set out in the corpus header, which is
likely to have a file name similar to "corphdr" or "CORPHDR".

Distribution of any part of the corpus under the terms of
the Licence must include a copy of the corpus header.
Distribution of this corpus text under the terms of the
Licence must include this header embodying this notice.

Permissions grantor for World:
East Anglian Daily Times Company (imprint) of Ipswich
</avail>
<date value=1997-03-10>
1997-03-10
</date>
</pubStmt>
<srcDesc>
<biblStr>
<monogr>
<title>
East Anglian daily times
</title>
<imprint n=EASTAN1>
<name>
East Anglian Daily Times Company
</name>
<pubPlace>
Ipswich
</pubPlace>
<date value=1993-03>
1993-03
</date>
</imprint>
</monogr>
</biblStr>
</srcDesc>

</fileDesc>
<encDesc>
<projDesc>
See the project description in the corpus header for
information about the British National Corpus project.
</projDesc>
<refsDecl>
Canonical references in the British National Corpus
are to text segment (&lt;s&gt;) elements, and
are constructed by taking the value of the n attribute
of the &lt;cdif&gt; element containing the target text,
and concatenating a dot separator, followed by the value
of the n attribute of the target &lt;s&gt; element.
</refsDecl>
<tagsDecl>
<tagUsage gi=c occurs=399>
</tagUsage>
<tagUsage gi=caption occurs=10>
</tagUsage>
<tagUsage gi=div1 occurs=18>
</tagUsage>
<tagUsage gi=head occurs=12>
</tagUsage>
<tagUsage gi=note occurs=5>
</tagUsage>
<tagUsage gi=p occurs=134>
</tagUsage>
<tagUsage gi=ptr occurs=14>
</tagUsage>
<tagUsage gi=reg occurs=1>
</tagUsage>
<tagUsage gi=s occurs=213>
</tagUsage>
<tagUsage gi=text occurs=1>
</tagUsage>
<tagUsage gi=w occurs=3397>
</tagUsage>
</tagsDecl>
</encDesc>
<profDesc>
<creation date=1993-03>
See &lt;biblStr&gt; for publication details.
</creation>
<txtClass>
<catRef target="allava2 alltyp3  wriaag0 wriad0 wriase0 wriaty2 wriaud3 wridom3 wrilev2 wrimed2 wripp922 wrisam0 wrista2 writas3  ">
<keywords>
<term>
(none)
</term>
</keywords>
</txtClass>
</profDesc>
<revDesc>
<change><date>2 Feb 1999</date>
<respStmt><resp>Patched</resp><name>Normalize S numbers</name></respStmt>
</change>
<change><date>16 Oct 98</date>
<respStmt><resp>Patched</resp><name>oneLinePatch</name></respStmt>
</change>
<change><date>10 May 97</date>
<respStmt><resp>Patched</resp><name>catRefPatch</name></respStmt>
</change><change n=s1>
<date value=1997-03-10>
1997-03-10
</date>
<respStmt>
<resp>
Amendments for initial release of sampler
</resp>
<name>
dominic
</name>
</respStmt>
</change>
<change n=1>
<date value=1994-11-24>
1994-11-24
</date>
<respStmt>
<resp>
Initial accession to corpus
</resp>
<name>
dominic
</name>
</respStmt>
</change>
</revDesc>
</header>
<text decls="CN001 QN000 SN002" complete=Y org=COMPO>
<note ed=OUP type=ED>
<s n=0001 p=Y><w MC>930303 </s>
</note>
<div1 complete=Y org=SEQ>
<head>
<s n=0002 p=Y><w NN1>Centre <w VVZ>brings <w NN1>health <w NN1>taboo <w II>into <w JJ>open </s>
</head>
<p>
<s n=0003 p=Y><w AT1>A <w JJ>NEW <w NN1>centre <w TO>to <w VVI>tackle <w AT>the <w JJ>unmentionable <w NN1>subject <w IO>of <w NN1>incontinence <w VHZ>has <w VVN>opened <w II>in <w NP1>Essex<c YSTP>. </s>
</p>
<p>
<s n=0004 p=Y><w AT>The <w NP1>Colne <w NN1>Centre <w II>at <w NP1>Severalls <w NNL1>Hospital<c YCOM>, <w NP1>Colchester<c YCOM>, <w VBZ>is <w VVN>aimed <w II>at <w AT>the <w JJ>estimated <w MC>ten <w NNU>per cent <w IO>of <w AT>the <w NN1>population <w PNQS>who <w VV0>suffer <w II>from <w NN1>incontinence<c YSTP>. </s>
</p>
<p>
<s n=0005 p=Y><w AT>The <w JJ>joint <w NN1>venture <w II>between <w MC>two <w NP1>NHS <w NN2>trusts <w II>in <w AT>the <w NN1>area <w VM>will <w VVI>provide <w NN1>help <w CC>and <w NN1>advice <w IF>for <w NN2>sufferers <w II>in <w AT>the <w NN1>county<c YSTP>. </s>
</p>
<p>
<s n=0006 p=Y><w II>At <w AT>the <w JJ>official <w NN1>opening <w RT>yesterday <w NP1>Colchester <w NN1>MP <w NP1>Bernard <w NP1>Jenkin <w VVD>praised <w AT>the <w NN1>work <w IO>of <w AT>the <w JJ>driving <w NN2>forces <w II>behind <w AT>the <w NN1>project <c YDSH>&mdash; <w NP1>Brenda <w NP1>Coward<c YCOM>, <w NN1>continence <w NN1>advisor <w IF>for <w NP1>Essex <w NN2>Rivers <w NN1>Healthcare <w NN1>Trust <w CC>and <w NP1>Mary <w NP1>Kennedy<c YCOM>, <w NN1>continence <w NN1>advisor <w IF>for <w NP1>North <w NP1>East <w NP1>Essex <w JJ>Mental <w NN1>Health <w NN1>Trust<c YSTP>. </s>
</p>
<p>
<s n=0007 p=Y><w MC1>One <w IO>of <w AT>the <w JJ>main <w NN2>tasks <w IO>of <w AT>the <w NN1>centre <w VM>will <w VBI>be <w TO>to <w VVI>help <w NN>people <w VVI>overcome <w APPGE>their <w NN1>embarrassment<c YSTP>. </s>
<s n=0008 p=Y><w AT1>A <w NN1>survey <w II>by <w NP1>MORI <w VVZ>estimates <w MC1>one <w II>in <w MC>five <w NN2>sufferers <w RR>never <w VV0>tell <w APPGE>their <w NN2>partners<c YSTP>. </s>
</p>
<p>
<s n=0009 p=Y><w JJ>Chief <w NN1>executive <w IO>of <w NP1>NEENHT <w NP1>Christopher <w NNL1>Bridge <w VVD>said<c YCOL>: <c YQUO>&bquo;<w NP1>Incontinence <w RR>unfortunately <w VVZ>remains <w AT1>a <w JJ>taboo <w NN1>subject<c YSTP>. </s>
<s n=0010 p=Y><w CCB>But <w EX>there <w VBR>are <w AT1>a <w NN1>number <w IO>of <w NN2>treatments <w DDQ>which <w VM>can <w VVI>make <w AT1>an <w JJ>enormous <w NN1>difference <w II>to <w AT>the <w NN1>quality <w IO>of <w NN>people<w GE>'s <w NN2>lives<c YSTP>.<c YQUO>&equo; </s>
</p>
</div1>
<div1 complete=Y org=SEQ>
<head>
<s n=0011 p=Y><w NN1>Attack <w II>on <w JJ>British <w NN1>breakfast </s>
</head>
<p>
<s n=0012 p=Y><w AT>THE <w JJ>traditional <w JJ>British <w NN1>breakfast <w IO>of <w NN2>eggs<c YCOM>, <w NN1>bacon <w CC>and <w NN2>bangers <w VVD>came <w II>under <w NN1>attack <w RT>yesterday <w II>on <w NN1>health <w NN2>grounds<c YSTP>. </s>
</p>
<p>
<s n=0013 p=Y><w NNB>Dr <w NP1>Jan <w NP1>Stjernsward<c YCOM>, <w NN1>chief <w IO>of <w AT>the <w NN1>World <w NN1>Health <w NN1>Organisation <w NN1>Cancer <w NN1>Unit<c YCOM>, <w VVD>said <w NP1>Britain <w VVD>needed <w TO>to <w VVI>change <w APPGE>its <w NN1>eating <w NN2>habits <w II>in <w AT>the <w NN1>battle <w II>against <w NN1>cancer<c YSTP>. </s>
</p>
<p>
<s n=0014 p=Y><w PPHS1>He <w VVD>told <w NN2>delegates <w II>at <w AT1>a <w NN1>conference <w II>in <w NP1>Kensington <w NN1>town <w NN1>hall <w II>about <w APPGE>his <w JJ>luxury <w NP1>London <w NN1>hotel<c YCOL>: <c YQUO>&bquo;<w APPGE>My <w NN1>goodness<c YCOM>, <w DDQ>what <w AT1>a <w NN1>breakfast<c YQUE>? </s>
<s n=0015 p=Y><w IW>With <w NN2>sausages<c YCOM>, <w NN1>ham <w CC>and <w NN2>eggs <c YDSH>&mdash; <w PPH1>it <w VBZ>is <w RG>so <w JJ>unhealthy<c YSTP>. </s>
</p>
<p>
<s n=0016 p=Y><c YQUO>&bquo;<w CS>When <w PPIS2>we <w VBDR>were <w NN2>hunters<c YCOM>, <w MC>two <w CC>and <w AT1>a <w DB>half <w NNO>million <w NNT2>years <w RA>ago <w NN1>roaming <w RP>round <w IW>with <w AT>the <w NN2>monkeys<c YCOM>, <w RR>only<w MCMC>15&ndash;20 <w NNU>per cent <w IO>of <w APPGE>our <w NN1>diet <w VBDZ>was <w NN1>fat<c YSTP>. </s>
</p>
<p>
<s n=0017 p=Y><c YQUO>&bquo;<w RT>Today <w PPH1>it <w VBZ>is<w NNU>40pc-plus <w CC>and <w PPIS2>we <w VM>must <w VVI>cut <w PPH1>it <w RP>down <w CS>if <w PPIS2>we <w VBR>are <w TO>to <w VVI>improve <w NN1>survival <w NN2>rates <w IO>of <w NN1>colon<c YCOM>, <w JJ>rectal<c YCOM>, <w NN1>breast <w CC>and <w JJ>other <w NN2>cancers <w II>as well as <w JJ>cardio-vascular <w NN1>disease<c YSTP>.<c YQUO>&equo; </s>
</p>
<p>
<s n=0018 p=Y><w NNB>Dr <w NP1>Stjernsward <w VVD>said <w NN2>children <w VHD>had <w TO>to <w VBI>be <w VVN>taught <w II>about <w AT>the <w NN1>need <w TO>to <w VVI>eat <w DAR>more <w JJ>fresh <w JJ>green <w NN2>vegetables <w CC>and <w NN1>fibre<c YSTP>. </s>
</p>
</div1>
<div1 complete=Y org=SEQ>
<head>
<s n=0019 p=Y><w NN1>Decision <w II>on <w NN1>water <w NN1>firm<w GE>'s <w NN1>plan <w VVN>put <w RP>off</s>
</head>
<p>
<s n=0020 p=Y><w NN2>PLANS <w IF>for <w NN1>water <w NN1>treatment <w NN>works <w TO>to <w VVI>reduce <w NN2>levels <w IO>of <w NN1>pollution <w II>in <w NN1>drinking <w NN1>water <w VH0>have <w VVN>upset <w NN2>councillors <w CS>because <w AT>the <w NN>works <w VM>would <w VBI>be <w VVN>situated <w II>in <w AT1>an <w NN1>area <w IO>of <w JJ>outstanding <w JJ>natural <w NN1>beauty<c YSTP>. </s>
</p>
<p>
<s n=0021 p=Y><w NP1>Essex <w NN1>Water <w NN1>Company <w VH0>have <w VVN>applied <w IF>for <w NN1>permission <w TO>to <w VVI>build <w MC>five <w JJ>new <w NN2>buildings <w II>on <w AT>the <w NN1>site <w IO>of <w APPGE>its <w JJ>existing <w NP1>Langham <w NNL1>Valley <w NN1>treatment <w VVZ>works <w II>in <w NP1>Boxted<c YSTP>. </s>
</p>
<p>
<s n=0022 p=Y><w AT>The <w NN1>water <w NN1>company <w VBZ>is <w II>under <w AT1>an <w NN1>obligation <w TO>to <w VVI>enhance <w VVG>drinking <w NN1>water <w NN2>standards <w II>because of <w AT1>a <w NP1>European <w NP1>Community <w NN1>directive <w CC>and <w VBZ>is <w JJ>liable <w TO>to <w VBI>be <w VVN>prosecuted <w II>by <w AT>the <w NP1>UK <w NN1>government <w CS>if <w AT>the <w NN2>improvements <w VH0>have <w XX>not <w VBN>been <w VVN>undertaken <w II>by <w AT>the <w NN1>end <w IO>of <w MC>1995<c YSTP>. </s>
</p>
<p>
<s n=0023 p=Y><w NN2>Members <w IO>of <w NP1>Colchester <w NNL1>Borough <w NN1>Council<w GE>'s <w NN1>planning <w NN1>committee <w VVD>heard <w NN2>objections <w II>from <w AT>the <w NP1>Dedham <w NNL1>Vale <w NN1>Society <w PNQS>who <w VV0>consider <w AT>the <w NN2>buildings <w VM>would <w VVI>create <w AT1>a <c YQUO>&bquo; <w JJ>monumental <w NN1>blot <w II>on <w AT>the <w NN1>landscape<c YQUO>&equo;<c YSTP>. </s>
</p>
<p>
<s n=0024 p=Y><w NP1>Dedham <w NN1>councillor <w NP1>George <w NP1>Williams <w VVG>commenting <w II>on <w AT>the <w NN2>plans <w VVD>said<c YCOL>: <c YQUO>&bquo; <w AT1>An <w JJ>industrial <w NN1>process <w VBZ>is <w VBG>being <w VVN>brought <w II>into <w AT>the <w NN1>heart <w IO>of <w AT>the <w NP1>Dedham <w NNL1>Valley<c YSTP>.<c YQUO>&equo; </s>
</p>
<p>
<s n=0025 p=Y><w NP1>Essex <w NN1>Water <w VBZ>is <w VVG>giving <w AT1>a <w NN1>presentation <w VVG>explaining <w APPGE>its <w NN2>reasons <w IF>for <w AT>the <w NN1>application <w CC>and <w VVG>answering <w NN2>questions <w II>on <w NPM1>March <w MC>25<c YSTP>. </s>
</p>
<p>
<s n=0026 p=Y><w AT>The <w NN1>planning <w NN1>committee <w VVD>decided <w II>on <w NPD1>Monday <w NNT1>evening <w TO>to <w VVI>defer <w APPGE>its <w NN1>decision <w II>about <w AT>the <w NN1>application <w II>until <w II>after <w DD1>that <w NN1>meeting<c YSTP>. </s>
</p>
<p>
<s n=0027 p=Y><w NN1>Permission <w VBZ>is <w VBG>being <w VVN>sought <w TO>to <w VVI>build <w AT1>an <w NN1>oxygen <w NN1>production <w NN1>building<c YCOM>, <w AT1>a <w NN1>pump <w NN1>house <w IW>with <w AT1>an <w NN1>ozonation <w CC>and <w NN1>filtration <w NN1>plant<c YCOM>, <w AT1>a <w NN1>chlorine <w NN1>house <w CC>and <w AT1>a <w NN1>nitrate <w NN1>removal <w NN1>plant<c YSTP>. </s>
</p>
<p>
<s n=0028 p=Y><w AT1>A <w JJ>new <w NN1>service <w NN1>road<c YCOM>, <w NN1>parking <w NN1>area <w CC>and <w NN1>tanker <w NN1>turning <w NN1>area <w VBZ>is <w RR>also <w VVN>proposed <w II>together with <w JJ>extensive <w JJ>new <w NN1>planting <w II>on <w AT>the <w NN1>periphery <w IO>of <w AT>the <w NN1>site<c YSTP>. </s>
</p>
<p>
<s n=0029 p=Y><w NN1>Water <w NN1>quality <w NN1>manager <w II>at <w NP1>Essex <w NN1>Water <w NP1>John <w NP1>Devall <w RT>yesterday <w VVD>said <w AT>the <w JJ>main <w NN1>part <w IO>of <w AT>the <w NN1>plant <w VBDZ>was <w IF>for <w NN1>pesticide <w NN1>removal <w CS>although <w AT>the <w NN1>company <w VBDZ>was <w VVG>making <w AT1>a <w NN1>provision <w IF>for <w AT1>a <w NN1>nitrate <w NN1>removal <w NN1>plant<c YSTP>. </s>
</p>
<p>
<s n=0030 p=Y><w DB>All <w NP1>Essex <w NN1>Water<w VBZ>'s <w NN1>water <w NN1>treatment <w NN>works <w VH0>have <w VVN>got <w TO>to <w VVI>comply <w IW>with <w AT>the <w NP1>EC <w NN1>water <w NN1>directive <w CC>and <w AT>the <w NN1>company <w VBZ>is <w VHG>having <w TO>to <w VVI>spend <w NNU>&pound;80 <w NNO>million <w II>on <w JJ>new <w NN2>buildings<c YCOM>, <w VVD>said <w NNB>Mr <w NP1>Devall<c YSTP>.</s>
</p>
<p>
<s n=0031 p=Y><c YQUO>&bquo;<w PPIS2>We <w VD0>do<w XX>n't <w VVI>believe <w CST>that <w AT>the <w NN1>proposal <w VM>will <w VVI>affect <w AT>the <w NN1>site <w IO>of <w NP1>Dedham <w NNL1>Vale<c YSCOL>; <w DAT>most <w IO>of <w PPH1>it <w VM>wo<w XX>n't <w VBI>be <w JJ>visible <w II>from <w AT>the <w NN2>roads<c YCOM>,<c YQUO>&equo; <w PPHS1>he <w VVD>said<c YSTP>. <ptr t=CF5CA000></s>
</p>
<caption id=CF5CA000>
<s n=0032 p=Y><w NN1>Nitrate <w VVZ>worries </s>
</caption>
<p>
<s n=0033 p=Y><w NN2>Councillors <w II>at <w AT>the <w NN1>planning <w NN1>meeting <w VHD>had <w VVN>expressed <w VVZ>worries <w CST>that <w NN2>nitrates <w VM>would <w VBI>be <w VVN>released <w II>into <w AT>the <w NN1>river <w NP1>Stour <w RRQ>when <w NN1>effluent <w II>from <w AT>the <w NN1>plant <w VVD>flowed <w II>into <w AT>the <w NN1>river<c YSTP>. </s>
</p>
<p>
<s n=0034 p=Y><w NNB>Mr <w NP1>Devall <w VVD>said <w CS>if <w AT>the <w NN1>nitrate <w NN1>removal <w NN1>plant <w NN1>house <w VBDZ>was <w VVN>built <w PPH1>it <w VM>would <w VVI>take <w NN1>water <w II>from <w AT>the <w NP1>Stour<c YCOM>, <w VV0>remove <w NN2>nitrates <w II>from <w NN1>part <w IO>of <w PPH1>it <w IF>for <w NN1>drinking <w NN1>water <w II>in <w NP1>Essex <w CC>and <w VVI>return <w AT>the <w NN1>rest <w II>into <w AT>the <w NP1>Stour<c YSTP>. </s>
</p>
<p>
<s n=0035 p=Y><w PPHS1>He <w VVD>said <w DD1>that <w NN1>portion <w VVN>returned <w II>to <w AT>the <w NN1>river <w VM>would <w VHI>have <w AT1>a <w JJR>higher <w NN1>concentration <w IO>of <w NN2>nitrates <w CCB>but <w VM>would <w VBI>be <w VVN>diluted <w RG>very <w RR>quickly<c YSTP>. </s>
</p>
</div1>
<div1 complete=Y org=SEQ>
<p>
<s n=0036 p=Y><w JJ>General <w NN1>situation<c YCOL>: <w NN2>Parts <w IO>of <w NP1>Scotland <w CC>and <w NP1>Northern <w NP1>Ireland <w VM>will <w VHI>have <w AT1>a <w NN1>touch <w IO>of <w NN1>frost <w RR>at first<c YCOM>, <w CCB>but <w DAT>most <w IO>of <w NP1>England <w CC>and <w NP1>Wales <w VM>should <w VBI>be <w JJ>frost free<c YSTP>. </s>
</p>
<p>
<s n=0037 p=Y><w PPH1>It <w VM>will <w VBI>be <w DD1>another <w JJ>cold<c YCOM>, <w CCB>but <w RR>largely <w JJ>dry <w NNT1>day <w II>across <w AT>the <w NN1>country<c YSTP>. </s>
</p>
<p>
<s n=0038 p=Y><w EX>There <w VM>will <w VBI>be <w AT1>a <w NN1>lot <w IO>of <w NN1>cloud <w RT>again <w II>over <w DA2>many <w NN2>parts <w IO>of <w NP1>England <w CC>and <w NP1>Wales<c YCOM>, <w CS>although <w PPH1>it <w VM>might <w VVI>become <w RR>a little <w JJR>brighter <w II>at <w NNT2>times<c YSTP>. </s>
</p>
<p>
<s n=0039 p=Y><w AT>The <w JJT>best <w IO>of <w DD>any <w JJ>bright <w NN1>weather <w VBZ>is <w VVN>expected <w II>in <w JJ>sheltered <w JJ>western <w NN2>areas <w IO>of <w NP1>Wales<c YCOM>, <w NP1>Scotland <w CC>and <w NP1>Northern <w NP1>Ireland<c YSTP>. </s>
</p>
<p>
<s n=0040 p=Y><w DD2>A few <w JJ>wintry <w NN2>showers <w VBR>are <w JJ>likely <w II>in <w JJ>eastern <w NN2>parts <w IO>of <w NP1>England <w CC>and <w NP1>Scotland<c YCOM>, <w RR>especially <w JJ>coastal <w NN2>counties<c YSTP>. </s>
</p>
<p>
<s n=0041 p=Y><w RR>Fairly <w JJ>windy <w RT>again <w II>in <w NP1>England <w CC>and <w NP1>Wales<c YCOM>, <w RR>especially <w II>in <w AT>the <w ND1>east<c YCOM>, <w DDQ>which <w VM>will <w VVI>make <w PPH1>it <w VVI>feel <w JJ>raw<c YSTP>. </s>
</p>
<p>
<s n=0042 p=Y><w NP1>East <w NP1>Anglia<c YCOL>: <w JJ>Scattered <w NN1>sleet <w CC>and <w NN1>snow <w NN2>showers<c YSTP>. </s>
<s n=0043 p=Y><w NN1>Wind <w ND1>north-east <w JJ>fresh <w II>to <w JJ>strong<c YSTP>. </s>
<s n=0044 p=Y><w JJ>Raw<c YSTP>. </s>
<s n=0045 p=Y><w JJ>Maximum <w NN1>temperature <w MC>4 <w RA>C <c YBL>(<w MC>39 <w RA>F<c YBR>)<c YSTP>.</s>
</p>
<p>
<s n=0046 p=Y><w NN1>Outlook <w IF>for <w RT>tomorrow <w CC>and <w NPD1>Friday<c YCOL>: <w NP1>Scotland <w VM>will <w VVI>become <w RGR>more <w JJ>cloudy <w IW>with <w AT1>a <w JJ>little <w NN1>rain<c YSTP>.</s>
<s n=0047 p=Y><w RR>Mostly <w JJ>dry <w CC>and <w NN1>cold <w RL>elsewhere<c YSTP>. </s>
</p>
<ptr t=CF5CA001>
<caption id=CF5CA001>
<s n=0048 p=Y><w NN1>SEA <w NN2>PASSAGES </s>
</caption>
<p>
<s n=0049 p=Y><w NP1>Southern <w NP1>North <w NNL1>Sea<c YCOL>: <w NN1>Wind <w ND1>north-east <w JJ>strong <w II>to <w II>near <w NN1>gale<c YSTP>. </s>
<s n=0050 p=Y><w DD2>A few <w JJ>wintry <w NN2>showers<c YSTP>. </s>
<s n=0051 p=Y><w NN1>Visibility <w JJ>good<c YSTP>. </s>
<s n=0052 p=Y><w NN1>Sea <w JJ>rough<c YCOM>, <w RR>perhaps <w RG>very <w JJ>rough<c YSTP>. <ptr t=CF5NT000></s>
</p>
<note id=CF5NT000 ed=OUP type=ED>
<s n=0053 p=Y><w MC>930304 </s>
</note>
</div1>
<div1 complete=Y org=SEQ>
<head>
<s n=0054 p=Y><w NP1>Sizewell <w ZZ1>C <w NN2>plans <w VV0>await <w NN1>outcome <w IO>of <w NN1>energy <w NN1>review </s>
</head>
<p>
<s n=0055 p=Y><w NN2>PLANS <w IF>for <w AT1>a <w NNU>&pound;1.6 <w NNO>billion <w NP1>Sizewell <w ZZ1>C <w JJ>nuclear <w NN1>power <w NN1>station <w VH0>have <w VBN>been <w RR>fully <w VVN>developed <w CC>and <w VBR>are <c YQUO>&bquo;<w II>on <w NN1>hold<c YQUO>&equo; <w II>pending <w AT>the <w NN1>outcome <w IO>of <w AT>the <w NN1>Government<w GE>'s <w NN1>energy <w NN1>review<c YCOM>, <w JJ>local <w NN1>community <w NN2>leaders <w VBDR>were <w VVN>told <w MD>last <w NNT1>night<c YSTP>. </s>
</p>
<p>
<s n=0056 p=Y><w AT>The <w NN2>plans <w VV0>include <w AT1>an <w JJ>environmental <w NN1>statement <w VVD>demanded <w II>by <w NP1>EC <w NN1>law<c YSTP>.</s>
</p>
<p>
<s n=0057 p=Y><w NP1>Sizewell <w ZZ1>B <w NN1>project <w NN1>manager <w NP1>Jim <w NP1>McFarlane <w VVD>told <w AT1>a <w NN1>meeting <w IO>of <w AT>the <w JJ>local <w NN1>community <w NN1>liaison <w NN1>committee<c YCOL>: <c YQUO>&bquo;<w PPIS2>We <w VV0>believe <w AT>the <w NN1>case <w IF>for <w DAR>more <w JJ>nuclear <w NN1>power <w VBZ>is <w JJ>irresistible <w CCB>but <w PPIS2>we <w VH0>have <w TO>to <w VVI>see <w DDQ>what <w AT>the <w NN1>Government <w VVZ>says <w II>before <w VVG>deciding <w CSW>whether <w TO>to <w VVI>submit <w AT>the <w ZZ1>C <w NN1>station <w NN1>application<c YSTP>. </s>
<s n=0058 p=Y><w AT>The <w RRR>sooner <w NP1>Sizewell <w ZZ1>C <w VBZ>is <w VVN>built <w AT>the <w JJR>better <w CS>as far as <w PPIS2>we<w VBR>'re <w JJ>concerned<c YSTP>. </s>
</p>
<p>
<s n=0059 p=Y><w NNB>Mr <w NP1>McFarlane <w VVD>said <w AT1>a <c YQUO>&bquo;<w JJ>temporary<c YQUO>&equo; <w NN1>jetty<c YCOM>, <w VVN>built <w TO>to <w VVI>allow <w JJ>large <w NN2>pieces <w IO>of <w NN1>plant <w TO>to <w VBI>be <w VVN>delivered <w II>to <w AT>the <w NN1>site<c YCOM>, <w VM>would <w XX>not <w VBI>be <w VVN>dismantled <w CS>before <w AT1>a <w NN1>decision <w VBDZ>was <w VVN>made <w II>on <w AT>the <w ZZ1>C <w NN1>station<c YSTP>. </s>
</p>
<p>
<s n=0060 p=Y><w JJ>Nuclear <w NN1>Electric <w NN2>officials <w VVN>agreed <w II>to <w AT1>a <w NN1>request <w II>from <w NP1>Leiston <w NN1>district <w NN1>councillor <w NP1>John <w NP1>Geater <w IF>for <w NN2>details <w IO>of <w AT>the <w NN2>costs <w IO>of <w JJ>nuclear <w NN1>generation <w TO>to <w VBI>be <w VVN>presented <w II>at <w AT1>a <w JJ>future <w NN1>meeting<c YSTP>. </s>
</p>
<p>
<s n=0061 p=Y><w AT>The <w JJ>state-owned <w NN1>company <w VVZ>claims <w CST>that <w JJ>nuclear <w VBZ>is <w AT>the <w JJT>best <w NN1>option <w IF>for <w NN1>power <w NN1>generation <w II>in terms of <w NN1>economics <w CC>and <w JJ>environmental <w NN1>impact<c YSTP>. </s>
<s n=0062 p=Y><w NN1>Environment <w NN2>groups <w VV0>disagree<c YSTP>. </s>
</p>
<p>
<s n=0063 p=Y><w AT>The <w NN1>meeting <w VVD>heard <w CST>that <w AT1>a <w NP1>Sizewell <w ZZ1>B <w NN1>worker <w VHD>had <w VBN>been <w VVN>sacked <w II>as <w AT1>a <w NN1>result <w IO>of <w AT1>a <w JJ>dangerous <w NN1>driving <w NN1>incident <w II>between <w NP1>Blythburgh <w CC>and <w AT>the <w NN1>site<c YSTP>. </s>
</p>
<p>
<s n=0064 p=Y><w JJ>Local <w NN2>residents <w VH0>have <w VBN>been <w VVG>pressing <w IF>for <w NN1>action <w TO>to <w VVI>curb <w AT>the <w NN1>speed <w CC>and <w NN1>behaviour <w IO>of <w DD>some <w NN2>drivers<c YSTP>. </s>
</p>
<p>
<s n=0065 p=Y><w DD1>Another <w NN1>worker <w VHZ>has <w VBN>been <w VVN>sacked <w IF>for <w AT1>a <w NN1>shoplifting <w NN1>offence <w II>in <w AT1>a <w JJ>local <w NN1>store<c YSTP>. </s>
</p>
</div1>
<div1 complete=Y org=SEQ>
<p>
<s n=0066 p=Y><w JJ>General<c YCOL>: <w NN1>Rain <w CC>and <w NN1>drizzle <w II>over <w ND1>north-west <w NP1>Scotland<c YCOM>, <w CC>and <w DD>some <w NN1>snow <w II>on <w AT>the <w NN2>hills <w RR>at first<c YCOM>, <w VM>will <w VVI>spread <w RL>south-eastwards <w II>across <w AT>the <w NN1>rest <w IO>of <w NP1>Scotland <w CC>and <w NP1>Northern <w NP1>Ireland<c YSTP>. </s>
</p>
<p>
<s n=0067 p=Y><w AT>The <w NN1>rain <w VM>will <w VVI>turn <w JJ>light <w CC>and <w JJ>patchy <w CC>and <w NN2>parts <w IO>of <w NP1>Northern <w NP1>Ireland <w VM>should <w VVI>stay <w JJ>dry<c YSTP>. </s>
</p>
<p>
<s n=0068 p=Y><w JJ>Scattered <w JJ>wintry <w NN2>showers <w II>over <w JJ>southern <w CC>and <w ND1>south-east <w NP1>England <w VM>should <w VVI>die <w RP>away <w II>in <w AT>the <w NNT1>morning<c YSTP>. </s>
<s n=0069 p=Y><w DAT>Most <w IO>of <w NP1>England <w CC>and <w NP1>Wales <w VM>should <w RT>then <w VBI>be <w JJ>dry <w CS>although <w DD>some <w JJ>light <w NN1>rain <w CC>or <w NN1>drizzle <w VBZ>is <w JJ>likely <w II>in <w JJ>northern <w NP1>England <w II>during <w AT>the <w NNT1>evening<c YSTP>. </s>
</p>
<p>
<s n=0070 p=Y><w PPH1>It <w VM>will <w VBI>be <w AT1>a <w JJR>brighter <w NNT1>day <w II>in <w AT>the <w NP1>South <w IW>with <w DD>some <w NN1>sunshine<c YSTP>. </s>
<s n=0071 p=Y><w JJ>Mild <w CC>and <w JJ>windy <w II>in <w AT>the <w NP1>North<c YCOM>, <w CC>and <w VVG>feeling <w RGR>less <w JJ>cold <w II>in <w JJ>southern <w NN2>parts<c YSTP>. </s>
</p>
<p>
<s n=0072 p=Y><w NP1>East <w NP1>Anglia<c YCOL>: <w JJ>Scattered <w JJ>wintry <w NN2>showers <w VVG>dying <w RP>out<c YCOM>, <w RT>then <w JJR>brighter<c YSTP>. </s>
<s n=0073 p=Y><w NN1>Wind <w ND1>north-east <w NN1>moderate <w II>to <w JJ>fresh <w VVG>backing <w ND1>north-west<c YSTP>. </s>
<s n=0074 p=Y><w NP1>Max <w NNU>5&ndash;7C <c YBL>(<w NNU>41&ndash;45F<c YBR>)<c YSTP>. </s>
</p>
<p>
<s n=0075 p=Y><w NN1>Outlook <w IF>for <w NNT1>tomorrow <w CC>and <w NPD1>Saturday<c YCOL>: </s>
</p>
<p>
<s n=0076 p=Y><w DD>Some <w JJ>light <w NN1>rain <w CC>or <w NN1>sleet <w II>on <w NPD1>Friday <w II>in <w AT>the <w ND1>north <w CC>and <w ND1>east<c YCOM>, <w RR>otherwise <w RR>mostly <w JJ>dry<c YSTP>. </s>
<s n=0077 p=Y><w VVG>Becoming <w JJR>milder<c YSTP>.<ptr t=CF5CA002></s>
</p>
<caption id=CF5CA002>
<s n=0078 p=Y><w NN1>SEA <w NN2>PASSAGES </s>
</caption>
<p>
<s n=0079 p=Y><w NP1>Southern <w NP1>North <w NP1>Sea<c YCOL>: <w NN1>Wind <w ND1>north-east <w JJ>moderate <w VVG>backing <w ND1>north-west <w RRR>later<c YSTP>. </s>
<s n=0080 p=Y><w DD2>A few <w JJ>wintry <w NN2>showers <w RR>at first<c YSTP>. </s>
<s n=0081 p=Y><w RR>Mainly <w JJ>good<c YSTP>. </s>
<s n=0082 p=Y><w NN1>Sea <w JJ>moderate<c YSTP>. </s>
</p>
</div1>
<div1 complete=Y org=SEQ>
<head>
<s n=0083 p=Y><w AT>No <w NN1>need <w TO>to <w VVI>get <w II>into <w AT1>a <w NN1>spin <w IW>with <w AT>the <w NN1>washing </s>
</head>
<p>
<s n=0084 p=Y><w DD1>THAT <w NN1>bane <w IO>of <w AT>the <w JJ>working <w NN1>mother<c YCOM>, <w AT>the <w NN1>repairman <w PNQS>who <w VVZ>promises <w TO>to <w VVI>call <c YQUO>&bquo;<w RT>sometime<c YQUO>&equo;<c YCOM>, <w VM>will <w RR>soon <w VBI>be <w AT1>a <w NN1>thing <w IO>of <w AT>the <w NN1>past <c YDSH>&mdash; <w II>according to <w NP1>BT <w NN2>boffins <w II>at <w NP1>Martlesham<c YSTP>. </s>
</p>
<p>
<s n=0085 p=Y><w NN2>Scientists <w VVG>carrying <w RP>out <w NN1>research <w II>into <w AT>the <w NN1>home <w IO>of <w AT>the <w NN1>future <w VV0>predict <w JJ>domestic <w NN2>appliances <w VM>will <w VBI>be <w JJ>able <w TO>to <c YQUO>&bquo;<w VVI>talk<c YQUO>&equo; <w II>to <w PPX2>each other<c YSTP>. </s>
</p>
<p>
<s n=0086 p=Y><w RR>So<c YCOM>, <w CS>if <w AT>the <w NN1>washing <w NN1>machine <w VVZ>goes <w RR>wrong<c YCOM>, <w PPH1>it <w VM>will <w VVI>diagnose <w AT>the <w NN1>problem <w PPX1>itself<c YCOM>, <w VVI>call <w AT>the <w NN1>repairman<c YCOM>, <w VVI>get <w AT1>a <w NN1>quote <w CC>and <w VVI>call <w APPGE>its <w NN1>owner <w II>at <w NN1>work <w TO>to <w VVI>find <w RP>out <w CSW>whether <w TO>to <w VVI>go <w RL>ahead<c YSTP>. </s>
</p>
<p>
<s n=0087 p=Y><w AT1>A <w NN1>videophone <w VM>will <w VVI>allow <w AT>the <w NN1>owner <w TO>to <w VVI>watch <w AT>the <w NN2>repairs <w VBG>being <w VVN>carried <w RP>out <w II>from <w APPGE>their <w NN1>office <w NN1>desk <w CC>and <w VVI>release <w NN1>payment <w CS>once <w AT>the <w NN1>machine <w VHZ>has <w VVN>checked <w PPX1>itself<c YSTP>. </s>
</p>
<p>
<s n=0088 p=Y><w VVN>Included <w II>in <w AT>the <w JJ>future <w NN1>home <w VM>will <w VBI>be <w NN2>devices <w DDQ>which <w VM>will <w VVI>allow <w AT>the <w NN1>owner <w TO>to <w VBI>be <w VVN>welcomed <w RL>home <w II>to <w NN2>lights <w VVN>switched <w RP>on<c YCOM>, <w NN2>curtains <w VVN>drawn <w CC>and <w RR>possibly <w RR>even <w AT>the <w NN1>dinner <w II>in <w AT>the <w NN1>oven<c YSTP>. </s>
</p>
<p>
<s n=0089 p=Y><w JJ>Virtual <w NN1>reality <w VM>will <w VVI>turn <w AT>the <w JJ>weekly <w NN1>supermarket <w NN1>shop <w II>into <w AT1>a <w NN1>pleasure <w TO>to <w VBI>be <w VVN>enjoyed <w II>from <w AT>the <w NN1>comfort <w IO>of <w AT>the <w NN1>armchair<c YSTP>. </s>
</p>
</div1>
<div1 complete=Y org=SEQ>
<p>
<s n=0090 p=Y><w JJ>New <w JJ>world-patented <w NN1>TV <w NN2>glasses <w VVN>designed <w II>by <w MC>two <w JJ>Hungarian <w NN2>engineers <w VV0>allow <w AT>the <w NN1>wearer <w TO>to <w VVI>walk <w CC>and <w NN1>watch <w NN1>television <w II>at <w AT>the <w DA>same <w NNT1>time<c YSTP>. </s>
<s n=0091 p=Y><w JJ>Mini <w NN1>television <w NN2>sets <w VBR>are <w VVN>fixed <w II>to <w AT>the <w NN2>spectacles<w GE>' <w NN2>frames <w CC>and <w AT>the <w NN1>image <w VBZ>is <w VVN>directed <w II>towards <w AT>the <w NN2>eyes <w II>by <w NN2>mirrors </s>
</p>
</div1>
<div1 complete=Y org=SEQ>
<head>
<s n=0092 p=Y><w NN1>Student <w NN2>stylists <w VBR>are <w VVN>put <w II>to <w AT>the <w NN1>test </s>
</head>
<p>
<s n=0093 p=Y><w RR>MORE than <w MC>100 <w NN2>students <w VVD>set <w RP>out <w TO>to <w VVI>prove <w PPHS2>they <w VBDR>were <w AT1>a <w NN1>cut <w II>above <w AT>the <w NN1>rest <w CS>when <w PPHS2>they <w VVD>took <w NN1>part <w II>in <w NP1>Colchester <w NNL1>Institute<w GE>'s <w MD>first <w NN1>hairdressing <w NN1>competition <w RT>yesterday<c YSTP>. </s>
</p>
<p>
<s n=0094 p=Y><w AT>The <w NN1>contest <w VBDZ>was <w JJ>open <w II>to <w DB>all <w NN1>hairdressing <w NN2>students <w II>at <w AT>the <w NN1>institute <w CCB>but <w RR>also <w VVD>included <w AT1>a <w NN1>category <w IF>for <w JJ>senior <w NN2>stylists <w CC>and <w NN1>salon <w NN2>owners<c YSTP>. </s>
</p>
<p>
<s n=0095 p=Y><w NN2>Awards <w VBDR>were <w II>on <w NN1>offer <w IF>for <w AT>the <w JJT>best <w NN1>use <w IO>of <w JJ>individual <w NN2>techniques<c YCOM>, <w II>plus <w AT1>a <w NN1>section <w VVN>judged <w II>on <w AT>the <c YQUO>&bquo;<w JJ>total <w NN1>look<c YQUO>&equo;<c YSTP>. </s>
</p>
<p>
<s n=0096 p=Y><w NN2>Judges <w VVD>said <w AT>the <w NN1>standard <w IO>of <w NN2>entries <w VHD>had <w VBN>been <w RR>exceptionally <w JJ>high <w IF>for <w DA>such <w AT1>an <w NN1>event<c YCOM>, <w IW>with <w DA2>many <w IO>of <w AT>the <w NN2>styles <w VVN>created <w VBG>being <c YQUO>&bquo;<w RG>very <w JJ>innovative<c YQUO>&equo;<c YSTP>. </s>
</p>
<p>
<s n=0097 p=Y><w NN2>Students <w II>on <w AT>the <w NN1>institute<w GE>'s <w JJ>two-year <w NN1>hairdressing <w CC>and <w NN1>beauty <w NN1>course <w VV0>learn <w AT>the <w NN1>art <w IO>of <w NN1>hairdressing<c YCOM>, <w NN1>cosmetic <w NN1>make-up<c YCOM>, <w NN1>manicure <w CC>and <w JJ>other <w JJ>beauty-related <w NN2>subjects<c YSTP>. </s>
</p>
<p>
<s n=0098 p=Y><w II>During <w AT>the <w MD>second <w NNT1>year<c YCOM>, <w VHG>having <w VVN>learned <w NN2>techniques <w II>in <w AT>the <w NN1>institute<w GE>'s <w DA>own <w JJ>well-equipped <w NN1>salon<c YCOM>, <w PPHS2>they <w VV0>gain <w NN1>work <w NN1>experience <w II>by <w VVG>spending <w MC>four <w NNT2>weeks <w II>in <w AT1>a <w JJ>commercial <w NN1>setting<c YSTP>. </s>
</p>
<ptr t=CF5CA003>
<ptr t=CF5NT001>
<caption id=CF5CA003>
<s n=0099 p=Y><w JJ>First-year <w NN1>hairdressing <w NN1>student <w NP1>Alison <w NP1>Parriss <w IW>with <w NN1>model <w NP1>Carrie <w NP1>Heckford </s>
</caption>
<note id=CF5NT001 ed=OUP type=ED>
<s n=0100 p=Y><w MC>930305 </s>
</note>
</div1>
<div1 complete=Y org=SEQ>
<head>
<s n=0101 p=Y><w NN1>TV <w NN1>idea <w IF>for <w JJ>level <w NN2>crossings </s>
</head>
<p>
<s n=0102 p=Y><w MC>TWO <w JJ>level <w NN2>crossings <w VVN>earmarked <w TO>to <w VVI>receive <w JJ>automatic <w NN2>barriers <w VM>could <w RT>now <w VBI>be <w VVN>fitted <w IW>with <w JJR>safer <w NN2>gates <w VVN>monitored <w II>on <w JJ>closed <w NN1>circuit <w NN1>television<c YSTP>. </s>
</p>
<p>
<s n=0103 p=Y><w NN1>County <w NN2>councillors <w VVD>voted <w RT>yesterday <w TO>to <w VVI>investigate <w AT>the <w NN1>cost <w IO>of <w VVG>providing <w AT>the <w RGR>more <w JJ>expensive <w NN2>gates <w II>at <w NN2>junctions <w II>in <w NP1>Colchester <w CC>and <w NP1>Kelvedon<c YSTP>. </s>
</p>
<p>
<s n=0104 p=Y><w AT>The <w NN1>move <w II>by <w AT1>a <w NN1>sub-committee <w IO>of <w AT>the <w NN1>council<w GE>'s <w NN2>highways <w NN1>committee <w VVZ>follows <w NN1>public <w NN1>concern <w II>over <w NN2>plans <w II>by <w JJ>British <w NN1>Rail <w TO>to <w VVI>replace <w JJ>manned <w NN2>barriers <w II>at <w NP1>Chitts <w NNL1>Hill<c YCOM>, <w NP1>Lexden<c YCOM>, <w CC>and <w NP1>Church <w NP1>Street<c YCOM>, <w NP1>Kelvedon<c YCOM>, <w IW>with <w JJ>automatic <w NN2>barriers <w VVG>covering <w RR>only <w DB>half <w AT>the <w NN1>carriageway<c YSTP>. </s>
</p>
<p>
<s n=0105 p=Y><w CS>Although <w APPGE>Her <w NN1>Majesty<w GE>'s <w NN1>Railway <w NN1>Inspectorate <w VHZ>has <w VVN>expressed <w NN1>concern <w II>over <w NN1>driver<w VBZ>'s <w NN1>behaviour <w II>at <w JJ>automatic <w NN2>barriers<c YCOM>, <w PPH1>it <w VVZ>believes <w PPHS2>they <w VV0>offer <w AT>the <w JJT>best <w NN1>blend <w IO>of <w NN1>safety <w CC>and <w NN1>cost <w NN1>efficiency<c YSTP>. </s>
</p>
<p>
<s n=0106 p=Y><w DD1>This <w VHZ>has <w XX>not <w VVN>satisfied <w NP1>Essex <w NN1>County <w NN1>Council<c YCOM>, <w DDQ>which <w VHZ>has <w VVN>produced <w NN>statistics <w VVG>showing <w JJ>fatal <w NN2>accidents <w VBR>are <w MC>four <w NNT2>times <w RRR>more <w RR>likely <w TO>to <w VVI>happen <w II>at <w JJ>automatic <w NN2>gates<c YSTP>. </s>
</p>
</div1>
<div1 complete=Y org=SEQ>
<head>
<s n=0107 p=Y><w JJ>Old <w NN1>craft <w VVZ>keeps <w NN1>sea <w II>at <w NN1>bay </s>
</head>
<p>
<s n=0108 p=Y><w CSA>As <w NP1>EAST <w NP1>Anglia <w VVZ>awaits <w MD>next <w NNT1>week<w VBZ>'s <w RR>potentially <w JJ>dangerous <w NP1>North <w NP1>Sea <w NN2>tides<c YCOM>, <w NN1>timber <w II>from <w AT>the <w NN1>region<w GE>'s <w JJ>small <w NN2>woodlands <w VBZ>is <w VBG>being <w VVN>harvested <w II>in <w AT>the <w JJ>constant <w NN1>fight <w TO>to <w VVI>keep <w NN1>flooding <w II>at <w NN1>bay<c YSTP>. </s>
</p>
<p>
<s n=0109 p=Y><c YQUO>&bquo;<w NN2>Mattresses<c YQUO>&equo; <w VVD>formed <w II>by <w NN2>bundles <w IO>of <w NN1>brushwood <w VBR>are <w VBG>being <w VVN>sunk<c YCOM>, <w VVN>weighed <w RP>down <w IW>with <w NN1>rock<c YCOM>, <w TO>to <w VVI>stabilise <w NN1>river <w NN2>beds <w CC>and <w VVI>protect <w NN2>banks <w II>from <w NN1>erosion<c YSTP>. </s>
</p>
<p>
<s n=0110 p=Y><w AT>The <w NN1>method <w VBZ>is <w RGR>more <w RR>environmentally <w JJ>friendly <w CSN>than <w VVG>building <w JJ>concrete <w NN2>walls<c YSTP>. </s>
<s n=0111 p=Y><w PPH1>It <w VBZ>is <w RR>also <w RG>very <w JJ>effective <w CC>and <w VHZ>has <w VBN>been <w VVN>practised <w II>in <w NP1>Holland <w IF>for <w NNT2>centuries<c YSTP>. </s>
</p>
<p>
<s n=0112 p=Y><w II>Despite <w JJ>modern-day <w NN1>technology<c YCOM>, <w AT>no <w JJR>better <w NN2>materials <w VH0>have <w VBN>been <w VVN>developed <w DDQ>which <w VM>will <w VDI>do <w AT>the <w NN1>job <w RR>as well<c YSTP>. </s>
</p>
<p>
<s n=0113 p=Y><w RR>More than <w MC>13,000 <w NN2>bundles <w IO>of <w NN1>brushwood<c YCOM>, <w VVN>harvested <w II>by <w VVG>coppicing <w NN1>hazel <w CC>and <w NN1>willow <w NN2>trees<c YCOM>, <w VBR>are <w VBG>being <w VVN>supplied <w II>to <w AT>the <w JJ>National <w NN2>Rivers <w NN1>Authority <w II>through <w AT>the <w JJ>Anglian <w NN1>Woodland <w NN1>Project <w DDQ>which <w VBZ>is <w VVN>supported <w II>by <w AT>the <w NN1>region<w VBZ>'s <w NN1>county <w NN2>councils<c YSTP>. </s>
</p>
<p>
<s n=0114 p=Y><w PPH1>It <w VHZ>has <w VBN>been <w VVN>set <w RP>up <w TO>to <w VVI>ensure <w AT>the <w NN1>future <w IO>of <w JJ>small <w NN2>woodlands <w II>by <w VVG>finding <w NN2>markets <w IF>for <w AT>the <w NN1>produce <w IO>of <w JJ>traditional <w NN1>management <w NN2>practices<c YCOM>, <w II>such as <w VVG>coppicing<c YCOM>, <w DDQ>which <w RR>also <w VV0>improve <w NN1>wildlife <w NN1>habitat<c YSTP>. </s>
</p>
<p>
<s n=0115 p=Y><w NN1>Brushwood <w VBZ>is <w VBG>being <w VVN>harvested <w II>from <w NN2>woodlands <w II>in <w AT>the <w NP1>Ipswich <w NN1>area <w II>by <w NP1>Bill <w NP1>Foreman <w CC>and <w JJ>other <w NN1>coppice <w NN2>workers <w TO>to <w VVI>help <w VVI>stabilise <w AT>the <w NN1>river <w NN1>bed <w IO>of <w AT>the <w JJ>Great <w NP1>Ouse <w II>in <w NP1>Cambridgeshire<c YSTP>. </s>
</p>
<p>
<s n=0116 p=Y><w II>In <w NP1>Essex<c YCOM>, <w AT>the <w NP1>NRA <w VBZ>is <w VVG>using <w NN1>brushwood<c YCOM>, <w II>including <w JJ>coppiced <w NN1>willow <w VVN>grown <w II>by <w NP1>Robert <w NP1>Goodwin <w II>at <w NP1>Kelvedon<c YCOM>, <w TO>to <w VVI>bolster <w NN1>flood <w NN2>defences <w II>near <w NP1>Burnham-on-Crouch<c YSTP>. </s>
</p>
<p>
<s n=0117 p=Y><w PPH1>It <w VBZ>is <w VBG>being <w VVN>made <w II>into <w NN2>groynes <w TO>to <w VVI>help <w VVI>re-create <w NN1>saltmarsh <w DDQ>which <w VHZ>has <w VBN>been <w VVN>eroded<c YSTP>. </s>
</p>
<p>
<s n=0118 p=Y><w AT>The <w NN1>brushwood <w NN2>groynes <w MC>200 <w NN2>yards <w RL>off-shore <w VV0>hold <w AT>the <w NN1>sediment <w CSA>as <w AT>the <w NN1>tide <w VVZ>retreats <w II>through <w PPHO2>them <w CC>and <w NP1>NRA <w NN2>officials <w VV0>hope <w PPH1>it <w VM>will <w VVI>lead <w II>to <w AT>the <w NN1>development <w IO>of <w JJ>new <w NN1>saltmarsh <w TO>to <w VVI>reduce <w AT>the <w NN1>impact <w IO>of <w NN2>waves <w VVG>hitting <w AT>the <w NN1>sea <w NN1>wall<c YSTP>. </s>
</p>
<p>
<s n=0119 p=Y><w NP1>Vince <w NP1>Thurkettle<c YCOM>, <w NN1>director <w IO>of <w AT>the <w JJ>Anglian <w NN1>Woodland <w NN1>Project<c YCOM>, <w VVD>said <w AT>the <w NN1>flood <w NN1>defence <w NN1>work<c YCOM>, <w NN1>grant <w VVD>aided <w II>by <w AT>the <w NN1>Ministry <w IO>of <w NN1>Agriculture<c YCOM>, <w VBDZ>was <w AT1>an <c YQUO>&bquo;<w JJ>exciting <w NN1>opportunity<c YQUO>&equo; <w IF>for <w NN1>woodland <w NN2>owners<c YSTP>. </s>
</p>
<p>
<s n=0120 p=Y><c YQUO>&bquo;<w AT1>An <w JJ>important <w JJ>modern <w NN1>task <w VBZ>is <w VBG>being <w VVN>carried <w RP>out <w II>in <w NN1>harness <w IW>with <w AT1>an <w JJ>ancient <w NN1>woodland <w NN1>system<c YCOM>,<c YQUO>&equo; <w PPHS1>he <w VVD>said<c YSTP>. <ptr t=CF5CA004></s>
</p>
<caption id=CF5CA004>
<s n=0121 p=Y><w NN1>Coppice <w NN1>worker <w NP1>Bill <w NP1>Foreman<c YCOM>, <w PNQS>who <w VBZ>is <w VVG>harvesting <w NN1>wood <w IF>for <w AT1>a <w NN1>river <w NN1>stabilisation <w NN1>project<c YCOM>, <w CC>and <w APPGE>his <w NN1>dog <w NP1>Meg <w II>in <w AT>the <w NN1>woodland <w PPHS1>he <w VVZ>manages <w II>near <w NP1>Sproughton </s>
</caption>
</div1>
<div1 complete=Y org=SEQ>
<head>
<s n=0122 p=Y><w NN1>Flood <w NN1>risk <w NN1>alert <w VVN>issued </s>
</head>
<p>
<s n=0123 p=Y><w NN2>FORECASTS <w IO>of <w AT>the <w JJT>highest <w NN2>tides <w IF>for <w NNT2>decades <w VH0>have <w VVN>prompted <w AT1>an <w NP1>Essex <w NN1>council <w TO>to <w VVI>distribute <w NN1>flood <w NN1>warning <w NN2>leaflets <w II>to <w NN>people <w VVG>living <w II>in <w JJ>low-lying <w NN2>areas<c YSTP>. </s>
</p>
<p>
<s n=0124 p=Y><w VVN>Prepared <w II>by <w NP1>Colchester <w NN1>Borough <w NN1>Council<c YCOM>, <w AT>the <w NN1>leaflet <w VVZ>explains <w RRQ>how <w TO>to <w VVI>protect <w PPX1>yourself <w CC>and <w APPGE>your <w NN1>home <w II>from <w NN1>flooding <w CC>and <w VVZ>lists <w JJ>useful <w NN1>phone <w NN2>numbers<c YSTP>. </s>
</p>
<p>
<s n=0125 p=Y><w NN2>Measures <w VVN>recommended <w II>in <w AT>the <w NN1>leaflet <w VV0>include <w VVG>preparing <w NN2>sandbags<c YCOM>, <w VVG>stocking <w RP>up <w IW>with <w JJ>essential <w NN2>foods<c YCOM>, <w VVG>checking <w NN1>insurance <w NN2>policies <w CC>and <w VVG>helping <w JJ>elderly <w CC>or <w JJ>infirm <w NN2>neighbours<c YSTP>. </s>
</p>
<p>
<s n=0126 p=Y><w AT>The <w NN1>council<w GE>'s <w NN1>emergency <w NN1>planning <w NN1>officer<c YCOM>, <w NP1>Mike <w NNL1>Hill<c YCOM>, <w VVD>said<c YCOL>: <c YQUO>&bquo;<w JJ>High <w NN2>tides <w RR>alone <w VD0>do<w XX>n't <w RR>necessarily <w VVI>mean <w NN1>flooding<c YCOM>, <w EX>there <w VHZ>has <w TO>to <w VBI>be <w AT1>a <w NN1>combination <w IO>of <w NN2>winds <w CC>and <w NN2>tides<c YCOM>, <w CC>and <w DD1>this <w VM>may <w XX>not <w VVI>happen<c YSTP>. <ptr t=CF5CA005></s>
</p>
<caption id=CF5CA005>
<s n=0127 p=Y><w NN2>Warnings </s>
</caption>
<p>
<s n=0128 p=Y><c YQUO>&bquo;<w PPIS2>We <w RR>certainly <w VD0>do<w XX>n't <w VVI>want <w TO>to <w VVI>alarm <w PN1>anyone<c YCOM>, <w CCB>but <w PPH1>it <w VBZ>is <w JJ>important <w IF>for <w NN>people <w TO>to <w VVI>know <w DDQ>what <w PPHS2>they <w VM>can <w VDI>do <w II>in <w NN1>advance <w TO>to <w VVI>prepare <w APPGE>their <w NN2>homes <w II>against <w NN1>damage<c YSTP>.<c YQUO>&equo; </s>
</p>
<p>
<s n=0129 p=Y><w CS>If <w JJ>necessary <w NN1>flood <w NN2>warnings <w VM>will <w VBI>be <w VVN>issued <w II>by <w AT>the <w JJ>National <w NN2>Rivers <w NN1>Authority <w CC>and <w NN2>police <w VM>will <w VVI>try <w TO>to <w VVI>warn <w NN2>residents <w VVG>using <w JJ>local <w NN1>radio<c YCOM>, <w NN1>television <w CC>and <w JJ>loud <w NN1>hailer <w NN2>vans <w VVG>touring <w NN1>risk <w NN2>areas<c YSTP>. </s>
</p>
<p>
<s n=0130 p=Y><w AT>The <w NN1>council <w VM>will <w VVI>provide <w NN1>emergency <w NN1>shelter <w IF>for <w PN1>anyone <w VVN>evacuated <w II>at <w NN2>schools<c YCOM>, <w NN1>village <w NN2>halls <w CC>or <w NN1>community <w NN2>centres<c YCOM>, <w CC>and <w VM>will <w VVI>help <w NN1>co-ordinate <w NN1>relief <w CC>and <w JJ>clear-up <w NN2>operations<c YSTP>. </s>
</p>
</div1>
<div1 complete=Y org=SEQ>
<p>
<s n=0131 p=Y><w JJ>General <w NN1>situation<c YCOL>: <w JJ>Sunny <w NN2>spells <w IW>with <w DD>some <w NN1>drizzle<c YSTP>. </s>
</p>
<p>
<s n=0132 p=Y><w JJ>Patchy <w JJ>light <w NN1>rain <w II>over <w JJ>central <w NN2>parts <w IO>of <w NP1>England <w CC>and <w NP1>Wales <w VM>will <w VVI>move <w RL>south <w CC>and <w VVI>peter <w RP>out <w II>by <w AT>the <w NNT1>evening<c YSTP>.</s>
<s n=0133 p=Y><w JJR>Drier <w NN1>weather <w VM>will <w VVI>follow <w RL>south <w IW>with <w JJ>sunny <w NN2>spells<c YCOM>, <w RR>particularly <w II>in <w AT>the <w RGR>more <w JJ>eastern <w NN2>parts<c YSTP>. </s>
</p>
<p>
<s n=0134 p=Y><w NP1>Northern <w NP1>England <w VM>will <w VBI>be <w RR>mostly <w JJ>dry<c YCOM>, <w IW>with <w AT>the <w JJT>best <w IO>of <w AT>the <w NN1>sun <w II>in <w AT>the <w ND1>east<c YSTP>. </s>
<s n=0135 p=Y><w JJR>Thicker <w NN1>cloud <w VM>will <w VVI>bring <w JJ>patchy <w NN1>drizzle <w II>over <w JJ>north-west-facing <w NN2>coasts <w CC>and <w NN2>hills<c YSTP>. </s>
</p>
<p>
<s n=0136 p=Y><w NP1>Scotland <w CC>and <w NP1>Northern <w NP1>Ireland <w VM>will <w VBI>be <w JJ>cloudy <w IW>with <w JJ>patchy <w NN1>drizzle <w II>in <w AT>the <w ND1>west<c YCOM>, <w CCB>but <w EX>there <w VM>will <w VBI>be <w JJ>sunny <w NN2>intervals<c YCOM>, <w RR>particularly <w II>in <w AT>the <w ND1>east<c YSTP>. </s>
</p>
<p>
<s n=0137 p=Y><w PPH1>It <w VM>will <w VVI>become <w JJR>milder <w RL>everywhere<c YSTP>. </s>
</p>
<p>
<s n=0138 p=Y><w NP1>East <w NP1>Anglia<c YCOL>: <w JJ>Patchy <w JJ>light <w NN1>rain<c YSTP>. </s>
<s n=0139 p=Y><w VVG>Becoming <w JJR>clearer <w CC>and <w JJ>dry <w II>from <w AT>the <w ND1>north<c YSTP>.</s>
<s n=0140 p=Y><w NN1>Wind <w ND1>north-west <w JJ>moderate<c YSTP>. </s>
<s n=0141 p=Y><w JJ>Cold <w NN1>start<c YCOM>, <w VVG>becoming <w JJR>milder <w RRR>later<c YSTP>. </s>
<s n=0142 p=Y><w JJ>Maximum <w NN1>temperature <w NNU>10C <c YBL>(<w NNU>50F<c YBR>)<c YSTP>. </s>
</p>
<p>
<s n=0143 p=Y><w NN1>Outlook <w IF>for <w RT>tomorrow <w CC>and <w NPD1>Sunday<c YCOL>: <w RR>Mainly <w JJ>dry <w CC>and <w JJ>mild<c YCOM>, <w IW>with <w JJ>sunny <w NN2>intervals <w II>after <w NN1>clearance <w IO>of <w DD>any <w JJ>early <w NN1>mist <w CC>or <w NN1>fog<c YSTP>. <ptr t=CF5CA006></s>
</p>
<caption id=CF5CA006>
<s n=0144 p=Y><w NN1>SEA <w NN2>PASSAGES </s>
</caption>
<p>
<s n=0145 p=Y><w NP1>Southern <w NP1>North <w NNL1>Sea<c YCOL>: <w NN1>Wind <w ND1>west<c YCOM>, <w VVG>becoming <w ND1>north-west<c YCOM>, <w JJ>moderate<c YCOM>, <w RR>locally <w JJ>fresh<c YSTP>. </s>
<s n=0146 p=Y><w JJ>Patchy <w NN1>rain <w RR>at first<c YSTP>. </s>
<s n=0147 p=Y><w NN1>Visibility <w JJ>moderate<c YCOM>, <w VVG>becoming <w JJ>good<c YSTP>. </s>
<s n=0148 p=Y><w NN1>Sea <w JJ>moderate<c YSTP>. </s>
</p>
</div1>
<div1 complete=Y org=SEQ>
<head>
<s n=0149 p=Y><w NN2>Slimmers<w GE>' <w NN1>joy <w II>at <w VVG>piling <w RP>on <w AT>the <w NN2>pounds </s>
</head>
<p>
<s n=0150 p=Y><w NN2>SLIMMERS <w VH0>have <w VVN>piled <w RP>on <w RR>more than <w AT1>a <w NNO>thousand <w NN2>pounds <w II>in <w RR>little <w RG>over <w AT1>a <w NNT1>month<c YLIP>&hellip; <w CC>and <w PPHS2>they <w VBR>are <w JJ>delighted<c YSTP>. </s>
</p>
<p>
<s n=0151 p=Y><w AT>The <w NN1>reason <w AT>the <w NN2>Weight-Watchers <w II>from <w NP1>Bury <w NP1>St <w NP1>Edmunds<c YCOM>, <w NP1>Haverhill<c YCOM>, <w NP1>Newmarket <w CC>and <w NP1>Saffron <w NP1>Walden <w VBR>are <w RG>so <w JJ>satisfied <w VBZ>is <w CST>that <w AT>the <w NN2>pounds <w PPHS2>they <w VVD>collected <c YDSH>&mdash; <w NNU>&pound;1,200 <w IO>of <w PPHO2>them <c YDSH>&mdash; <w VM>will <w DB>all <w VBI>be <w VVG>going <w II>to <w NN1>charity<c YSTP>. </s>
</p>
<p>
<s n=0152 p=Y><w NN1>Class <w NN1>leader <w NP1>Lynn <w NP1>Lawrence<c YCOM>, <w MC>46<c YCOM>, <w IO>of <w NP1>Hawthorne <w NNL1>Close<c YCOM>, <w NP1>Bury<c YCOM>, <w VHZ>has <w VVN>handed <w AT>the <w NN1>money <w RP>over <w II>to <w AT>the <w JJ>Imperial <w NN1>Cancer <w NN1>Research <w NN1>Fund<c YSTP>. </s>
</p>
<p>
<s n=0153 p=Y><w NNB>Mrs <w NP1>Lawrence<c YCOM>, <w PNQS>who <w VVD>lost <w MC>five <w NN1>stone <w II>within <w AT1>a <w NNT1>year <w IO>of <w VVG>joining <w NN1>Weight <w NN2>Watchers <w II>in <w MC>1985<c YCOM>, <w VVD>said <w MC>250 <w NN1>Weight <w NN2>Watchers <w VHD>had <w VVN>raised <w AT>the <w NN1>money <w II>in <w AT1>a <w NN>series <w IO>of <w NN1>table <w NN2>sales<c YCOM>, <w NN2>raffles <w CC>and <w VVZ>draws<c YSTP>. </s>
</p>
<p>
<s n=0154 p=Y><w II>Following <w AT>the <w NN1>donation <w II>at <w AT>the <w JJ>United <w NN1>Reform <w NNL1>Church<c YCOM>, <w II>in <w NP1>Whiting <w NNL1>Street<c YCOM>, <w NP1>Bury<c YCOM>, <w PPHS1>she <w VVD>said <w AT>the <w NN1>money <w VBDZ>was <w AT1>a <w NN1>tribute <w II>to <w JJ>local <w NN2>slimmers <w PNQS>who <w VHD>had <w VVN>developed <w NN1>cancer <w II>in <w AT>the <w JJ>past <w NNT1>year<c YSTP>. <ptr t=CF5CA007></s>
</p>
<caption id=CF5CA007>
<s n=0155 p=Y><w NN1>Research </s>
</caption>
<p>
<s n=0156 p=Y><c YQUO>&bquo;<w AT>The <w NN1>amount <w PPIS2>we <w VVD>raised <w VBDZ>was <w JJ>magic<c YSTP>. </s>
<s n=0157 p=Y><w PPIS1>I <w RR>never <w VVD>thought <w PPIS2>we <w VM>would <w VVI>get <w PN1>anything <w II>like <w DD1>that <w NN1>sum<c YCOM>, <w CCB>but <w AT>the <w NN1>nature <w IO>of <w AT>the <w NN1>charity <w RR>obviously <w VVD>struck <w RL>home<c YSTP>. </s>
<s n=0158 p=Y><w AT>The <w NP1>ICRF <w VBZ>is <w DA>such <w AT1>a <w JJ>worthy <w NN1>cause <w CC>and <w DDQ>what <w VVZ>makes <w PPH1>it <w RR>particularly <w RR>so <w VBZ>is <w CST>that <w PPH1>it <w VVZ>uses <w JJ>just <w NNU>8p <w II>out of <w AT1>every <w NNU>&pound;1 <w IF>for <w NN1>administration<c YCOM>, <w NN1>meaning <w NNU>92p <w RR>really <w VVZ>goes <w II>on <w VVG>advancing <w AT>the <w NN1>research<c YCOM>,<c YQUO>&equo; <w PPHS1>she <w VVD>said<c YSTP>. </s>
</p>
<p>
<s n=0159 p=Y><w NN1>Cancer <w NN1>Research<w GE>'s <w NN1>area <w JJ>retail <w NN1>manager <w NP1>Pam <w NP1>McMillan <w VVD>said <w AT>the <w NN1>organisation <w VVD>relied <w RR>almost <w RR>totally <w II>on <w NN1>public <w NN1>generosity <w TO>to <w VVI>fund <w APPGE>its <w JJ>vital <w NN1>work<c YSTP>. </s>
</p>
<p>
<s n=0160 p=Y><c YQUO>&bquo;<w PPIS2>We<w VBR>'re <w RG>very <w JJ>grateful <w II>to <w NN1>Weight <w NN2>Watchers <w IF>for <w DD1>this <w JJ>magnificent <w NN1>sum<c YSTP>. </s>
<s n=0161 p=Y><w PN1>Everyone <w PNQS>who <w VVD>took <w NN1>part <w VM>can <w VBI>be <w JJ>sure <w CST>that <w AT>the <w NN1>money <w PPHS2>they <w VVD>helped <w TO>to <w VVI>raise <w VM>will <w VBI>be <w RR>well <w VVN>spent <w II>in <w AT>the <w NN1>fight <w II>against <w NN1>cancer<c YCOM>,<c YQUO>&equo; <w PPHS1>she <w VVD>said<c YSTP>. <ptr t=CF5NT002></s>
</p>
<note id=CF5NT002 ed=OUP type=ED>
<s n=0162 p=Y><w MC>930315 </s>
</note>
</div1>
<div1 complete=Y org=SEQ>
<p>
<s n=0163 p=Y><w JJ>General <w NN1>situation<c YCOL>: <w RR>Much <w IO>of <w NP1>England <w CC>and <w NP1>Wales <w VM>will <w VHI>have <w AT1>a <w JJ>dry<c YCOM>, <w JJ>bright <w NNT1>day<c YSTP>. </s>
<s n=0164 p=Y><w AT>The <w JJT>best <w IO>of <w AT>the <w NN1>sunshine <w VM>will <w VBI>be <w II>in <w AT>the <w ND1>south <w CC>and <w ND1>east<c YSTP>. </s>
<s n=0165 p=Y><w JJ>Western <w NN2>coasts <w VM>will <w VBI>be <w RGR>more <w JJ>cloudy<c YCOM>, <w RR>perhaps <w IW>with <w AT1>a <w JJ>little <w NN1>drizzle<c YSTP>. </s>
</p>
<p>
<s n=0166 p=Y><w JJ>Northern <w NN2>counties <w IO>of <w NP1>England <w CC>and <w ND1>north <w NP1>Wales <w VM>will <w VVI>become <w JJ>cloudy <w IW>with <w NN1>rain <w II>in <w NN2>places <w II>by <w NNT1>midnight<c YSTP>. </s>
</p>
<p>
<s n=0167 p=Y><w JJ>Southern <w CC>and <w JJ>eastern <w NP1>Scotland <w CC>and <w DA1>much <w IO>of <w NP1>Northern <w NP1>Ireland <w VM>will <w VVI>start <w JJ>dry<c YCOM>, <w CCB>but <w NN1>rain <w II>over <w ND1>northwest <w NP1>Scotland <w VM>will <w VVI>spread <w ND1>southeast <w II>during <w AT>the <w NNT1>day<c YSTP>. </s>
</p>
<p>
<s n=0168 p=Y><w RR>Mainly <w JJ>dry <w NN1>weather <w VM>will <w VVI>follow <w II>to <w ND1>northwest <w NP1>Scotland <w DD1>this <w NNT1>afternoon <w CC>and <w II>to <w DAT>most <w IO>of <w NP1>Northern <w NP1>Ireland <w CC>and <w NP1>Scotland <w II>by <w NNT1>midnight<c YSTP>. </s>
<s n=0169 p=Y><w NN2>Temperatures <w VM>will <w VBI>be <w JJ>similar <w II>to <w NNT1>yesterday<w GE>'s <w RR>generally<c YSTP>. </s>
</p>
<p>
<s n=0170 p=Y><w NP1>East <w NP1>Anglia<c YCOL>: <w JJ>Patchy <w NN1>fog <w RR>at first<c YSTP>. </s>
<s n=0171 p=Y><w JJ>Dry <w IW>with <w JJ>sunny <w NN2>spells<c YSTP>. </s>
<s n=0172 p=Y><w NN1>Wind <w ND1>south <w II>to <w ND1>southwest <w JJ>light<c YSTP>. </s>
<s n=0173 p=Y><w NN1>Max <w NN1>temp <w MC>15 <w II>to <w NNU>17C <c YBL>(<w MC>59 <w II>to <w NNU>63F<c YBR>)<c YSTP>. </s>
</p>
<p>
<s n=0174 p=Y><w NN1>Outlook <w IF>for <w NNT1>tomorrow <w CC>and <w NPD1>Wednesday<c YCOL>: <w NN2>Outbreaks <w IO>of <w NN1>rain <w VM>will <w VVI>spread <w II>across <w JJ>northern <w NN2>parts<c YSTP>. </s>
<s n=0175 p=Y><w JJ>Patchy <w NN1>rain <w II>over <w NP1>England <w CC>and <w NP1>Wales <w II>on <w NPD1>Tuesday <w VM>will <w VBI>be <w VVN>followed <w II>by <w JJ>dry<c YCOM>, <w JJ>bright <w NN1>weather<c YSTP>. <ptr t=CF5CA008></s>
</p>
<caption id=CF5CA008>
<s n=0176 p=Y><w NN1>SEA <w NN2>PASSAGES </s>
</caption>
<p>
<s n=0177 p=Y><w JJ>Southern <w NP1>North <w NNL1>Sea<c YCOL>: <w NN1>Wind <w RR>mainly <w ND1>south <w JJ>light <w II>to <w JJ>moderate<c YSTP>. </s>
<s n=0178 p=Y><w JJ>Fair<c YSTP>. </s>
<s n=0179 p=Y><w NN1>Visibility <w RR>mostly <w JJ>good<c YSTP>. </s>
<s n=0180 p=Y><w NN1>Sea <w NN1>slight<c YSTP>. </s>
</p>
</div1>
<div1 complete=Y org=SEQ>
<head>
<s n=0181 p=Y><w NN1>Brain <w NN2>injuries <w NN1>group <w VVZ>launches <w NN1>appeal <w TO>to <w VVI>extend <w APPGE>its <w NNT1>day <w NN1>centre </s>
</head>
<p>
<s n=0182 p=Y><w AT1>A <w JJ>VOLUNTARY <w NN1>group <w DDQ>which <w VVZ>provides <w NN1>support <w IF>for <w AT>the <w NN2>families <w IO>of <w NN>people <w PNQS>who <w VH0>have <w VVN>suffered <w NN1>brain <w NN2>injuries <w VHZ>has <w VVN>launched <w AT1>an <w NN1>appeal <w TO>to <w VVI>extend <w APPGE>its <w NNT1>day <w NN1>centre<c YSTP>. </s>
</p>
<p>
<s n=0183 p=Y><w NP1>Colchester <w CC>and <w NP1>North <w NP1>East <w NP1>Essex <w NP1>Headway<c YCOM>, <w DDQ>which <w VBZ>is <w VVN>affiliated <w II>to <w AT>the <w JJ>National <w NN1>Head <w NN2>Injuries <w NN1>Association<c YCOM>, <w VHZ>has <w VBN>been <w VVG>seeking <w JJR>larger <w NN2>premises <w IF>for <w DD>some <w NNT1>time<c YSTP>. </s>
</p>
<p>
<s n=0184 p=Y><w RT>Now <w PPH1>it <w VHZ>has <w VVN>submitted <w AT1>a <w NN1>planning <w NN1>application <w TO>to <w VVI>double <w AT>the <w NN1>size <w IO>of <w APPGE>its <w JJ>current <w NN2>premises <c YDSH>&mdash; <w AT1>a <w JJ>two-bedroom <w NN1>bungalow <w II>on <w AT>the <w NP1>Severalls <w NNL1>Hospital <w NN1>site <w II>in <w NP1>Colchester<c YSTP>. </s>
</p>
<p>
<s n=0185 p=Y><w RG>Up to <w MC>15 <w NN>people <w IW>with <w NN1>brain <w NN2>injuries <w VBR>are <w VVN>cared <w IF>for <w II>at <w AT>the <w NN1>centre <w DD1>each <w NNT1>day <w CC>and <w AT>the <w JJ>main <w NN1>feature <w IO>of <w AT>the <w NN1>extension <w VM>will <w VBI>be <w AT1>a <w JJ>large <w NN1>activity <w NN1>room<c YSTP>. </s>
</p>
<p>
<s n=0186 p=Y><w PPH1>It <w VM>will <w RR>also <w VVI>provide <w AT1>a <w JJ>new <w NN1>wheelchair <w NN1>ramp<c YCOM>, <w NN1>porch <w CC>and <w NN1>entrance <w NN1>area <w CC>and <w VVI>allow <w AT1>an <w NN1>existing <w NN1>room <w TO>to <w VBI>be <w VVN>designated <w II>as <w AT1>a <w JJ>quiet <w NN1>area<c YSTP>. </s>
</p>
<p>
<s n=0187 p=Y><w AT>The <w NN1>scheme <w VBZ>is <w VVN>expected <w TO>to <w VVI>cost <w AT1>a <w NN1>total <w IO>of <w RG>about <w NNU>&pound;100,000 <w CC>and <w AT>the <w NP1>Headway <w NN1>group <w VM>can <w VVI>press <w RL>ahead <w IW>with <w NN1>building <w NN1>work<c YCOM>, <w NN2>thanks <w II>to <w NN1>funding <w II>from <w AT>the <w NP1>Catalyst <w NN1>Trust <w NN1>charity<c YSTP>. </s>
</p>
<p>
<s n=0188 p=Y><w RR>However<c YCOM>, <w PPH1>it <w RR>still <w VVZ>needs <w TO>to <w VVI>raise <w NNU>&pound;25,000 <w II>towards <w AT>the <w NNU>&pound;80,000 <w NN1>construction <w NN1>cost <w II>plus <w NNU>&pound;20,000 <w IF>for <w NN1>furnishing <w CC>and <w NN1>equipment<c YCOM>, <w DD>some <w IO>of <w DDQ>which <w PPH1>it <w VVZ>hopes <w VM>will <w VBI>be <w VVN>donated <w II>by <w JJ>local <w NN2>companies<c YSTP>. </s>
</p>
<p>
<s n=0189 p=Y><w AT1>A <w NN1>variety <w IO>of <w JJ>fund-raising <w NN2>schemes <w VBR>are <w VVN>planned<c YCOM>, <w II>including <w AT1>a <w NN1>relaunch <w IO>of <w AT>the <w NN1>group<w GE>'s <w NNU1>Penny <w NN1>Appeal<c YCOM>, <w DDQ>which <w NN2>encourages <w NN>people <w TO>to <w VVI>collect <w CC>and <w VVI>donate <w APPGE>their <w JJ>small <w NN1>change<c YSTP>. </s>
</p>
<p>
<s n=0190 p=Y><w NN2>Plans <w IF>for <w AT>the <w NN1>extension <w VM>will <w VBI>be <w II>on <w NN1>display <w II>at <w AT>the <w NN1>group<w GE>'s <w JJ>annual <w NN1>meeting <w II>on <w NPM1>March <w MC>25<c YCOM>, <w RRQ>when <w JJ>future <w NN2>activities <w CC>and <w NN1>fund-raising <w VM>will <w VBI>be <w VVN>discussed<c YSTP>. </s>
</p>
<p>
<s n=0191 p=Y><w DAR>More <w NN>people <w VBR>are <w RR>also <w VVN>wanted <w TO>to <w VVI>act <w II>as <w NN1>committee <w NN2>members <c YDSH>&mdash; <w RR>particularly <w NN>people <w PNQS>who <w VH0>have <w AT1>a <w NN1>relative <w IW>with <w AT1>a <w NN1>brain <w NN1>injury <c YDSH>&mdash; <w TO>to <w VVI>help <w AT>the <w JJ>present <w NN1>team <w II>by <w VVG>spreading <w AT>the <w NN1>workload<c YSTP>. <ptr t=CF5NT003></s>
</p>
<note id=CF5NT003 ed=OUP type=ED>
<s n=0192 p=Y><w MC>930316 </s>
</note>
</div1>
<div1 complete=Y org=SEQ>
<head>
<s n=0193 p=Y><w JJ>New <w NN1>type <w IO>of <w NN1>refrigerator <w VBZ>is <w JJ>harmless <w II>to <w NN1>ozone <w NN1>layer </s>
</head>
<p>
<s n=0194 p=Y><w NN1>PRODUCTION <w IO>of <w AT>the <w NN1>world<w GE>'s <w MD>first <w JJ>ozone-friendly <w NN1>refrigerator <w VVD>began <w RT>yesterday <w II>at <w AT1>a <w JJ>small <w JJ>eastern <w JJ>German <w NN1>factory<c YSTP>. </s>
</p>
<p>
<s n=0195 p=Y><w PPH1>It <w VBZ>is <w JJ>free <w IO>of <reg ed=OUCS sic=cholorflourocarbon> <w NN1>chlorflourocarbon </reg> <w NN2>gases <w DDQ>which <w VH0>have <w VBN>been <w VVN>used <w TO>to <w VVI>cool <w DAT>most <w NN2>fridges <w IF>for <w NNT2>decades<c YSTP>. </s>
<s n=0196 p=Y><w PPHS2>They <w VBR>are <w VBG>being <w VVN>banned <w RL>worldwide <w II>from <w MC>1996 <w CS>because <w PPHS2>they <w VV0>cause <w NN2>holes <w II>in <w AT>the <w NN1>ozone <w NN1>layer<c YCOM>, <w AT>the <w NN1>shield <w DDQ>which <w VVZ>protects <w AT>the <w NN1>earth <w II>from <w AT>the <w NN1>sun<w GE>'s <w JJ>harmful <w JJ>ultraviolet <w NN2>rays<c YSTP>. </s>
</p>
<p>
<s n=0197 p=Y><w AT>The <w JJ>new <w NN1>fridge <w VVZ>uses <w AT1>a <w NN1>mix <w IO>of <w NN1>butane <w CC>and <w NN1>propane <w NN2>gases <w II>as <w NN2>coolants<c YSTP>. </s>
</p>
</div1>
<div1 complete=Y org=SEQ>
<p>
<s n=0198 p=Y><w JJ>General <w NN1>situation<c YCOL>: <w JJ>Cloudy <w II>in <w NP1>Scotland <w CC>and <w NP1>Northern <w NP1>Ireland <w IW>with <w NN1>rain<c YCOM>, <w JJ>heavy <w II>at <w NNT2>times <w RR>especially <w II>over <w AT>the <w NN2>hills<c YSTP>. </s>
</p>
<p>
<s n=0199 p=Y><w AT>The <w NN1>rain <w VM>will <w VVI>move <w RL>south <w II>into <w JJ>northern <w NP1>England <w CC>and <w NP1>Wales <w II>during <w AT>the <w NNT1>afternoon<c YCOM>, <w IW>with <w JJR>heavier <w NN2>bursts <w II>over <w JJ>western <w NN2>coasts<c YSTP>. </s>
</p>
<p>
<s n=0200 p=Y><w JJR>Clearer <w NN2>conditions <w VM>will <w VVI>follow <w II>into <w JJ>northern <w NP1>Scotland <w CC>and <w AT>the <w JJ>northern <w NN2>isles <w RRR>later<c YSTP>. </s>
</p>
<p>
<s n=0201 p=Y><w JJ>Southern <w NN2>counties<c YCOM>, <w CS>although <w RG>rather <w JJ>cloudy<c YCOM>, <w VM>will <w VBI>be <w RR>mainly <w JJ>dry<c YCOM>, <w II>except for <w NN2>outbreaks <w IO>of <w NN1>drizzle <w II>over <w ND1>south-west <w NP1>England <w CC>and <w NP1>South <w NP1>Wales<c YSTP>. </s>
<s n=0202 p=Y><w DA2>Many <w JJ>sheltered <w JJ>central <w CC>and <w JJ>south-eastern <w NN2>areas <w VM>might <w VVI>stay <w JJ>dry <w IW>with <w RR>perhaps <w DD>some <w JJ>sunny <w NN2>intervals<c YSTP>. </s>
</p>
<p>
<s n=0203 p=Y><w PPH1>It <w VM>will <w VVI>become <w JJ>windy <w II>in <w AT>the <w RR>far <w ND1>north <w CC>and <w ND1>west<c YCOM>, <w CC>and <w VVI>remain <w JJ>warm <w II>in <w AT>the <w ND1>south<c YSTP>. </s>
</p>
<p>
<s n=0204 p=Y><w NP1>East <w NP1>Anglia<c YCOL>: <w RG>Rather <w JJ>cloudy<c YCOM>, <w RR>mainly <w JJ>dry<c YCOM>, <w DD>some <w JJ>sunny <w NN2>intervals<c YSTP>. </s>
<s n=0205 p=Y><w NN1>Wind <w JJ>light <w II>to <w JJ>moderate <w ND1>south-west<c YSTP>. </s>
<s n=0206 p=Y><w JJ>Maximum <w NN1>temperature <w NNU>14C <c YBL>(<w NNU>57F<c YBR>)<c YSTP>. </s>
</p>
<p>
<s n=0207 p=Y><w NN1>Outlook <w IF>for <w NNT1>tomorrow <w CC>and <w NPD1>Thursday<c YCOL>: <w NN2>Outbreaks <w IO>of <w NN1>rain <w II>in <w AT>the <w ND1>north <w RT>tomorrow<c YSTP>. </s>
<s n=0208 p=Y><w JJR>Drier <w IW>with <w JJ>sunny <w NN2>spells <w IF>for <w DB>all <w NN2>areas <w II>on <w NPD1>Thursday <w NNT1>afternoon<c YSTP>. <ptr t=CF5CA009></s>
</p>
<caption id=CF5CA009>
<s n=0209 p=Y><w NN1>SEA <w NN2>PASSAGES </s>
</caption>
<p>
<s n=0210 p=Y><w NP1>Southern <w NP1>North <w NNL1>Sea<c YCOL>: <w NN1>Wind <w ND1>south-west <w CC>or <w ND1>west<c YCOM>, <w JJ>moderate <w II>to <w JJ>fresh<c YSTP>. </s>
<s n=0211 p=Y><w JJ>Fair<c YSTP>. </s>
<s n=0212 p=Y><w NN1>Visibility <w JJ>good<c YSTP>. </s>
<s n=0213 p=Y><w NN1>Sea <w JJ>moderate<c YSTP>. </s>
</p>
</div1>
</text>
</bncDoc>
